repo2kaniko/__init__.py
repo2kaniko/_version.py
repo2kaniko/kaniko.py
repo2kaniko-0.1.0.dist-info/LICENSE
repo2kaniko-0.1.0.dist-info/METADATA
repo2kaniko-0.1.0.dist-info/WHEEL
repo2kaniko-0.1.0.dist-info/entry_points.txt
repo2kaniko-0.1.0.dist-info/top_level.txt
repo2kaniko-0.1.0.dist-info/RECORD
