Metadata-Version: 2.1
Name: repo2kaniko
Version: 0.1.0
Summary: Repo2docker Kaniko builder
Home-page: https://github.com/manics/repo2kaniko
Author: Simon Li
License: BSD
Project-URL: Documentation, https://repo2docker.readthedocs.io
Keywords: reproducible science environments docker
Classifier: Environment :: Console
Classifier: Intended Audience :: Developers
Classifier: Intended Audience :: System Administrators
Classifier: Intended Audience :: Science/Research
Classifier: License :: OSI Approved :: BSD License
Classifier: Programming Language :: Python
Classifier: Programming Language :: Python :: 3
Requires-Python: >=3.8
License-File: LICENSE
Requires-Dist: jupyter-repo2docker >=2023.6.0
Requires-Dist: repo2podman >=0.2.0
